CG22079UNO/__init__.py
CG22079UNO/bisection.py
CG22079UNO/crammer.py
CG22079UNO/ejemplos.py
CG22079UNO/eliminacion_gauss.py
CG22079UNO/gauss_jordan.py
CG22079UNO/gauss_seidel.py
CG22079UNO/jacobi.py
CG22079UNO/lu_decomposition.py
CG22079UNO-1.2.6.dist-info/LICENSE
CG22079UNO-1.2.6.dist-info/METADATA
CG22079UNO-1.2.6.dist-info/WHEEL
CG22079UNO-1.2.6.dist-info/top_level.txt
CG22079UNO-1.2.6.dist-info/RECORD
