Metadata-Version: 2.1
Name: CG22079UNO
Version: 1.2.6
Summary: Librería para resolver sistemas de ecuaciones con métodos numéricos
Home-page: https://github.com/tuusuario/CG22079UNO
Author: Gloria Elena Castellanos Garcia
Author-email: CG22070@ues.edu.sv
Classifier: Programming Language :: Python :: 3
Classifier: License :: OSI Approved :: MIT License
Requires-Python: >=3.6
License-File: LICENSE
Requires-Dist: numpy
Requires-Dist: scipy
